rumchat_actor/__init__.py
rumchat_actor/actions.py
rumchat_actor/commands.py
rumchat_actor/misc.py
rumchat_actor/static.py
rumchat_actor/utils.py
rumchat_actor-3.5.0.dist-info/METADATA
rumchat_actor-3.5.0.dist-info/WHEEL
rumchat_actor-3.5.0.dist-info/licenses/LICENSE.txt
rumchat_actor-3.5.0.dist-info/RECORD
