Metadata-Version: 2.4
Name: rumchat_actor
Version: 3.5.0
Summary: Automatically interact with your Rumble livestream chats.
Project-URL: Homepage, https://github.com/thelabcat/rum-chat-actor
Project-URL: Issues, https://github.com/thelabcat/rumble-api-wrapper-py/issues
Project-URL: Documentation, https://thelabcat.github.io/rumble-chat-actor/
Author-email: Wilbur Jaywright <zargulthewizard@outlook.com>
License-File: LICENSE.txt
Keywords: bot,chat,livestream,rumble
Classifier: Development Status :: 4 - Beta
Classifier: License :: OSI Approved :: GNU Affero General Public License v3
Classifier: Operating System :: OS Independent
Classifier: Programming Language :: Python :: 3
Requires-Python: >=3.8
Requires-Dist: cocorum
Requires-Dist: moviepy
Requires-Dist: obsws-python
Requires-Dist: pygame
Requires-Dist: requests
Requires-Dist: standard-pipes
Requires-Dist: talkey
